factcheckr/__init__.py
factcheckr/__main__.py
factcheckr/cli.py
factcheckr/core.py
factcheckr-1.0.1.dist-info/licenses/LICENSE
factcheckr-1.0.1.dist-info/METADATA
factcheckr-1.0.1.dist-info/WHEEL
factcheckr-1.0.1.dist-info/entry_points.txt
factcheckr-1.0.1.dist-info/top_level.txt
factcheckr-1.0.1.dist-info/RECORD
