Metadata-Version: 2.4
Name: factcheckr
Version: 1.0.1
Summary: AI-powered fact-checking tool with fallback mechanisms
Author-email: FactCheckr Team <contact@factcheckr.dev>
Project-URL: Homepage, https://github.com/factcheckr/factcheckr
Project-URL: Bug Reports, https://github.com/factcheckr/factcheckr/issues
Project-URL: Source, https://github.com/factcheckr/factcheckr
Project-URL: Documentation, https://github.com/factcheckr/factcheckr#readme
Keywords: fact-checking,ai,nlp,verification,truth,claims
Classifier: Development Status :: 5 - Production/Stable
Classifier: Intended Audience :: Developers
Classifier: Intended Audience :: Education
Classifier: Intended Audience :: Science/Research
Classifier: License :: OSI Approved :: MIT License
Classifier: Operating System :: OS Independent
Classifier: Programming Language :: Python :: 3
Classifier: Programming Language :: Python :: 3.7
Classifier: Programming Language :: Python :: 3.8
Classifier: Programming Language :: Python :: 3.9
Classifier: Programming Language :: Python :: 3.10
Classifier: Programming Language :: Python :: 3.11
Classifier: Programming Language :: Python :: 3.12
Classifier: Topic :: Scientific/Engineering :: Artificial Intelligence
Classifier: Topic :: Text Processing :: Linguistic
Classifier: Topic :: Internet :: WWW/HTTP :: Dynamic Content
Requires-Python: >=3.7
License-File: LICENSE
Requires-Dist: requests>=2.25.0
Provides-Extra: dev
Requires-Dist: pytest>=6.0; extra == "dev"
Requires-Dist: pytest-cov>=2.0; extra == "dev"
Requires-Dist: black>=21.0; extra == "dev"
Requires-Dist: flake8>=3.8; extra == "dev"
Requires-Dist: mypy>=0.800; extra == "dev"
Requires-Dist: pre-commit>=2.0; extra == "dev"
Dynamic: license-file
